explorerdev/__init__.py
explorerdev/client.py
explorerdev/server.py
explorerdev-0.1.0.dist-info/licenses/LICENSE
explorerdev-0.1.0.dist-info/METADATA
explorerdev-0.1.0.dist-info/WHEEL
explorerdev-0.1.0.dist-info/entry_points.txt
explorerdev-0.1.0.dist-info/top_level.txt
explorerdev-0.1.0.dist-info/RECORD
